rms_starcat-1.0.2.dist-info/licenses/LICENSE
starcat/__init__.py
starcat/_version.py
starcat/py.typed
starcat/spice.py
starcat/starcatalog.py
starcat/ucac4.py
starcat/ybsc.py
rms_starcat-1.0.2.dist-info/METADATA
rms_starcat-1.0.2.dist-info/WHEEL
rms_starcat-1.0.2.dist-info/top_level.txt
rms_starcat-1.0.2.dist-info/RECORD
