Metadata-Version: 2.4
Name: rms-starcat
Version: 1.0.2
Summary: Star catalog database
Maintainer-email: "Robert S. French" <rfrench@seti.org>
License: Apache-2.0
Project-URL: Homepage, https://github.com/SETI/rms-starcat
Project-URL: Documentation, https://rms-starcat.readthedocs.io/en/latest
Project-URL: Repository, https://github.com/SETI/rms-starcat
Project-URL: Source, https://github.com/SETI/rms-starcat
Project-URL: Issues, https://github.com/SETI/rms-starcat/issues
Keywords: UCAC4,YBSC,star
Classifier: Development Status :: 5 - Production/Stable
Classifier: Natural Language :: English
Classifier: Topic :: Scientific/Engineering
Classifier: Topic :: Scientific/Engineering :: Astronomy
Classifier: Topic :: Software Development :: Libraries :: Python Modules
Classifier: Topic :: Utilities
Classifier: License :: OSI Approved :: Apache Software License
Classifier: Programming Language :: Python :: 3.9
Classifier: Programming Language :: Python :: 3.10
Classifier: Programming Language :: Python :: 3.11
Classifier: Programming Language :: Python :: 3.12
Classifier: Programming Language :: Python :: 3.13
Classifier: Operating System :: MacOS :: MacOS X
Classifier: Operating System :: POSIX :: Linux
Classifier: Operating System :: Microsoft :: Windows
Requires-Python: >=3.9
License-File: LICENSE
Requires-Dist: cspyce
Requires-Dist: numpy
Dynamic: license-file
